pywebhdfs/__init__.py
pywebhdfs/errors.py
pywebhdfs/operations.py
pywebhdfs/webhdfs.py
tests/__init__.py
tests/test_errors.py
tests/test_webhdfs.py
pywebhdfs_fork-0.4.15.dist-info/AUTHORS
pywebhdfs_fork-0.4.15.dist-info/LICENSE
pywebhdfs_fork-0.4.15.dist-info/METADATA
pywebhdfs_fork-0.4.15.dist-info/WHEEL
pywebhdfs_fork-0.4.15.dist-info/top_level.txt
pywebhdfs_fork-0.4.15.dist-info/RECORD
