Metadata-Version: 2.1
Name: pywebhdfs-fork
Version: 0.4.15
Summary: 
